AUTHORS.rst
CONTRIBUTING.rst
HISTORY.rst
LICENSE
MANIFEST.in
README.rst
VERSION
setup.cfg
setup.py
docs/Makefile
docs/authors.rst
docs/conf.py
docs/contributing.rst
docs/gitlab_artifacts_downloader.rst
docs/history.rst
docs/index.rst
docs/installation.rst
docs/make.bat
docs/modules.rst
docs/readme.rst
docs/usage.rst
gitlab_artifacts_downloader/__init__.py
gitlab_artifacts_downloader/gitlab_artifacts_downloader.py
gitlab_artifacts_downloader.egg-info/PKG-INFO
gitlab_artifacts_downloader.egg-info/SOURCES.txt
gitlab_artifacts_downloader.egg-info/dependency_links.txt
gitlab_artifacts_downloader.egg-info/not-zip-safe
gitlab_artifacts_downloader.egg-info/requires.txt
gitlab_artifacts_downloader.egg-info/top_level.txt
requirements/ci.txt
requirements/prod.txt
requirements/test.txt
tests/__init__.py
tests/test_gitlab_artifacts_downloader.py